{
    "annotations": {
        "list": [
            {
                "builtIn": 1,
                "datasource": {
                    "type": "grafana",
                    "uid": "-- Grafana --"
                },
                "enable": true,
                "hide": true,
                "iconColor": "rgba(0, 211, 255, 1)",
                "name": "Annotations & Alerts",
                "target": {
                    "limit": 100,
                    "matchAny": false,
                    "tags": [],
                    "type": "dashboard"
                },
                "type": "dashboard"
            }
        ]
    },
    "editable": true,
    "fiscalYearStartMonth": 0,
    "graphTooltip": 0,
    "id": 7,
    "links": [],
    "liveNow": false,
    "panels": [
        {
            "datasource": {
                "type": "prometheus",
                "uid": "PBFA97CFB590B2093"
            },
            "fieldConfig": {
                "defaults": {
                    "color": {
                        "mode": "palette-classic"
                    },
                    "custom": {
                        "axisCenteredZero": false,
                        "axisColorMode": "text",
                        "axisLabel": "",
                        "axisPlacement": "auto",
                        "barAlignment": 0,
                        "drawStyle": "line",
                        "fillOpacity": 0,
                        "gradientMode": "none",
                        "hideFrom": {
                            "legend": false,
                            "tooltip": false,
                            "viz": false
                        },
                        "lineInterpolation": "linear",
                        "lineWidth": 1,
                        "pointSize": 5,
                        "scaleDistribution": {
                            "type": "linear"
                        },
                        "showPoints": "auto",
                        "spanNulls": false,
                        "stacking": {
                            "group": "A",
                            "mode": "none"
                        },
                        "thresholdsStyle": {
                            "mode": "off"
                        }
                    },
                    "mappings": [],
                    "thresholds": {
                        "mode": "absolute",
                        "steps": [
                            {
                                "color": "green",
                                "value": null
                            },
                            {
                                "color": "red",
                                "value": 80
                            }
                        ]
                    },
                    "unit": "s"
                },
                "overrides": []
            },
            "gridPos": {
                "h": 9,
                "w": 12,
                "x": 0,
                "y": 0
            },
            "id": 2,
            "options": {
                "legend": {
                    "calcs": [],
                    "displayMode": "list",
                    "placement": "bottom",
                    "showLegend": true
                },
                "tooltip": {
                    "mode": "single",
                    "sort": "none"
                }
            },
            "targets": [
                {
                    "datasource": {
                        "type": "prometheus",
                        "uid": "PBFA97CFB590B2093"
                    },
                    "editorMode": "code",
                    "expr": "time() - cache_last_updated",
                    "legendFormat": "__auto",
                    "range": true,
                    "refId": "A"
                }
            ],
            "title": "Cache Age",
            "type": "timeseries"
        },
        {
            "datasource": {
                "type": "prometheus",
                "uid": "PBFA97CFB590B2093"
            },
            "description": "excluding /metrics",
            "fieldConfig": {
                "defaults": {
                    "color": {
                        "mode": "palette-classic"
                    },
                    "custom": {
                        "axisCenteredZero": false,
                        "axisColorMode": "text",
                        "axisLabel": "",
                        "axisPlacement": "auto",
                        "barAlignment": 0,
                        "drawStyle": "line",
                        "fillOpacity": 0,
                        "gradientMode": "none",
                        "hideFrom": {
                            "legend": false,
                            "tooltip": false,
                            "viz": false
                        },
                        "lineInterpolation": "linear",
                        "lineWidth": 1,
                        "pointSize": 5,
                        "scaleDistribution": {
                            "type": "linear"
                        },
                        "showPoints": "auto",
                        "spanNulls": false,
                        "stacking": {
                            "group": "A",
                            "mode": "none"
                        },
                        "thresholdsStyle": {
                            "mode": "off"
                        }
                    },
                    "mappings": [],
                    "thresholds": {
                        "mode": "absolute",
                        "steps": [
                            {
                                "color": "green",
                                "value": null
                            },
                            {
                                "color": "red",
                                "value": 80
                            }
                        ]
                    }
                },
                "overrides": []
            },
            "gridPos": {
                "h": 9,
                "w": 12,
                "x": 12,
                "y": 0
            },
            "id": 4,
            "options": {
                "legend": {
                    "calcs": [],
                    "displayMode": "list",
                    "placement": "bottom",
                    "showLegend": true
                },
                "tooltip": {
                    "mode": "single",
                    "sort": "none"
                }
            },
            "targets": [
                {
                    "datasource": {
                        "type": "prometheus",
                        "uid": "PBFA97CFB590B2093"
                    },
                    "editorMode": "code",
                    "expr": "http_code_total{job=\"sceta-server\", path!=\"/metrics\"}",
                    "legendFormat": "{{code}} {{path}}",
                    "range": true,
                    "refId": "A"
                }
            ],
            "title": "HTTP Response Codes",
            "type": "timeseries"
        },
        {
            "datasource": {
                "type": "prometheus",
                "uid": "PBFA97CFB590B2093"
            },
            "fieldConfig": {
                "defaults": {
                    "color": {
                        "mode": "palette-classic"
                    },
                    "custom": {
                        "axisCenteredZero": false,
                        "axisColorMode": "text",
                        "axisLabel": "",
                        "axisPlacement": "auto",
                        "barAlignment": 0,
                        "drawStyle": "line",
                        "fillOpacity": 0,
                        "gradientMode": "none",
                        "hideFrom": {
                            "legend": false,
                            "tooltip": false,
                            "viz": false
                        },
                        "lineInterpolation": "linear",
                        "lineWidth": 1,
                        "pointSize": 5,
                        "scaleDistribution": {
                            "type": "linear"
                        },
                        "showPoints": "auto",
                        "spanNulls": false,
                        "stacking": {
                            "group": "A",
                            "mode": "none"
                        },
                        "thresholdsStyle": {
                            "mode": "off"
                        }
                    },
                    "mappings": [],
                    "thresholds": {
                        "mode": "absolute",
                        "steps": [
                            {
                                "color": "green",
                                "value": null
                            },
                            {
                                "color": "red",
                                "value": 80
                            }
                        ]
                    },
                    "unit": "s"
                },
                "overrides": []
            },
            "gridPos": {
                "h": 8,
                "w": 12,
                "x": 0,
                "y": 9
            },
            "id": 6,
            "options": {
                "legend": {
                    "calcs": [],
                    "displayMode": "list",
                    "placement": "bottom",
                    "showLegend": true
                },
                "tooltip": {
                    "mode": "single",
                    "sort": "none"
                }
            },
            "targets": [
                {
                    "datasource": {
                        "type": "prometheus",
                        "uid": "PBFA97CFB590B2093"
                    },
                    "editorMode": "code",
                    "expr": "api_latency_sum / api_latency_count",
                    "legendFormat": "__auto",
                    "range": true,
                    "refId": "A"
                }
            ],
            "title": "511 API Latency",
            "type": "timeseries"
        },
        {
            "datasource": {
                "type": "prometheus",
                "uid": "PBFA97CFB590B2093"
            },
            "fieldConfig": {
                "defaults": {
                    "color": {
                        "mode": "palette-classic"
                    },
                    "custom": {
                        "axisCenteredZero": false,
                        "axisColorMode": "text",
                        "axisLabel": "",
                        "axisPlacement": "auto",
                        "barAlignment": 0,
                        "drawStyle": "line",
                        "fillOpacity": 0,
                        "gradientMode": "none",
                        "hideFrom": {
                            "legend": false,
                            "tooltip": false,
                            "viz": false
                        },
                        "lineInterpolation": "linear",
                        "lineWidth": 1,
                        "pointSize": 5,
                        "scaleDistribution": {
                            "type": "linear"
                        },
                        "showPoints": "auto",
                        "spanNulls": false,
                        "stacking": {
                            "group": "A",
                            "mode": "none"
                        },
                        "thresholdsStyle": {
                            "mode": "off"
                        }
                    },
                    "mappings": [],
                    "thresholds": {
                        "mode": "absolute",
                        "steps": [
                            {
                                "color": "green",
                                "value": null
                            },
                            {
                                "color": "red",
                                "value": 80
                            }
                        ]
                    },
                    "unit": "none"
                },
                "overrides": []
            },
            "gridPos": {
                "h": 8,
                "w": 12,
                "x": 12,
                "y": 9
            },
            "id": 7,
            "options": {
                "legend": {
                    "calcs": [],
                    "displayMode": "list",
                    "placement": "bottom",
                    "showLegend": true
                },
                "tooltip": {
                    "mode": "single",
                    "sort": "none"
                }
            },
            "targets": [
                {
                    "datasource": {
                        "type": "prometheus",
                        "uid": "PBFA97CFB590B2093"
                    },
                    "editorMode": "code",
                    "expr": "api_response_codes_total",
                    "legendFormat": "__auto",
                    "range": true,
                    "refId": "A"
                }
            ],
            "title": "511 API Response Codes",
            "type": "timeseries"
        }
    ],
    "refresh": "",
    "revision": 1,
    "schemaVersion": 38,
    "style": "dark",
    "tags": [],
    "templating": {
        "list": []
    },
    "time": {
        "from": "now-15m",
        "to": "now"
    },
    "timepicker": {},
    "timezone": "",
    "title": "SCEta",
    "uid": "cfonSOpIk",
    "version": 2,
    "weekStart": ""
}